hass_web_proxy_lib/__init__.py
hass_web_proxy_lib/py.typed
hass_web_proxy_lib/tests/__init__.py
hass_web_proxy_lib/tests/conftest.py
hass_web_proxy_lib/tests/test_proxy_lib.py
hass_web_proxy_lib/tests/utils.py
hass_web_proxy_lib-0.0.6.dist-info/LICENSE
hass_web_proxy_lib-0.0.6.dist-info/METADATA
hass_web_proxy_lib-0.0.6.dist-info/WHEEL
hass_web_proxy_lib-0.0.6.dist-info/RECORD
